codex_taps/__init__.py
codex_taps/__main__.py
codex_taps/decrypter.py
codex_taps-0.1.2.dist-info/WHEEL
codex_taps-0.1.2.dist-info/METADATA
codex_taps-0.1.2.dist-info/RECORD
