Metadata-Version: 2.1
Name: codex-taps
Version: 0.1.2
Summary: This is a utility tool for efficiently conduting the final round of CODEx.
Home-page: https://github.com/Arpan-206/special-tribble-codex-final
License: MIT
Author: Arpan Pandey
Author-email: arpan@hackersreboot.tech
Requires-Python: >=3.6,<4.0
Classifier: License :: OSI Approved :: MIT License
Classifier: Programming Language :: Python :: 3
Classifier: Programming Language :: Python :: 3.10
Classifier: Programming Language :: Python :: 3.6
Classifier: Programming Language :: Python :: 3.7
Classifier: Programming Language :: Python :: 3.8
Classifier: Programming Language :: Python :: 3.9
Requires-Dist: cryptography (>=37.0.4,<38.0.0)
Requires-Dist: requests (>=2.28.1,<3.0.0)
Requires-Dist: rich (>=12.5.1,<13.0.0)
Requires-Dist: typer (>=0.6.1,<0.7.0)
Project-URL: Repository, https://github.com/Arpan-206/special-tribble-codex-final
